<?xml version="1.0" encoding="UTF-8"?>
<!--
  ~ This file is part of Shiro J Bot.
  ~ Copyright (C) 2019-2021  Yago Gimenez (KuuHaKu)
  ~
  ~ Shiro J Bot is free software: you can redistribute it and/or modify
  ~ it under the terms of the GNU General Public License as published by
  ~ the Free Software Foundation, either version 3 of the License, or
  ~ (at your option) any later version.
  ~
  ~ Shiro J Bot is distributed in the hope that it will be useful,
  ~ but WITHOUT ANY WARRANTY; without even the implied warranty of
  ~ MERCHANTABILITY or FITNESS FOR A PARTICULAR PURPOSE.  See the
  ~ GNU General Public License for more details.
  ~
  ~ You should have received a copy of the GNU General Public License
  ~ along with Shiro J Bot.  If not, see <https://www.gnu.org/licenses/>
  -->

<persistence version="2.0"
             xmlns="http://java.sun.com/xml/ns/persistence" xmlns:xsi="http://www.w3.org/2001/XMLSchema-instance"
             xsi:schemaLocation="http://java.sun.com/xml/ns/persistence http://java.sun.com/xml/ns/persistence/persistence_2_0.xsd">
    <persistence-unit name="main">
        <provider>org.hibernate.jpa.HibernatePersistenceProvider</provider>

        <!-- SHIRO -->
        <class>com.kuuhaku.model.persistent.shiro.Anime</class>
        <class>com.kuuhaku.model.persistent.shiro.Card</class>
        <class>com.kuuhaku.model.persistent.shiro.GlobalProperty</class>

        <!-- GUILD -->
        <class>com.kuuhaku.model.persistent.guild.ColorRole</class>
        <class>com.kuuhaku.model.persistent.guild.GoodbyeSettings</class>
        <class>com.kuuhaku.model.persistent.guild.GuildConfig</class>
        <class>com.kuuhaku.model.persistent.guild.GuildSettings</class>
        <class>com.kuuhaku.model.persistent.guild.LevelRole</class>
        <class>com.kuuhaku.model.persistent.guild.WelcomeSettings</class>
        <class>com.kuuhaku.model.persistent.guild.StarredMessage</class>

        <!-- USER -->
        <class>com.kuuhaku.model.persistent.user.Account</class>
        <class>com.kuuhaku.model.persistent.user.AccountSettings</class>
        <class>com.kuuhaku.model.persistent.user.DynamicProperty</class>
        <class>com.kuuhaku.model.persistent.user.Kawaipon</class>
        <class>com.kuuhaku.model.persistent.user.KawaiponCard</class>
        <class>com.kuuhaku.model.persistent.user.Profile</class>
        <class>com.kuuhaku.model.persistent.user.ProfileSettings</class>
        <class>com.kuuhaku.model.persistent.user.Transaction</class>
        <class>com.kuuhaku.model.persistent.user.VoiceData</class>
        <class>com.kuuhaku.model.persistent.user.StashedCard</class>
        <class>com.kuuhaku.model.persistent.user.AccessToken</class>
        <class>com.kuuhaku.model.persistent.user.Couple</class>
        <class>com.kuuhaku.model.persistent.user.Title</class>
        <class>com.kuuhaku.model.persistent.user.AccountTitle</class>
        <class>com.kuuhaku.model.persistent.user.LocalizedTitle</class>

        <!-- SHOUKAN -->
        <class>com.kuuhaku.model.persistent.shoukan.Deck</class>
        <class>com.kuuhaku.model.persistent.shoukan.Evogear</class>
        <class>com.kuuhaku.model.persistent.shoukan.Field</class>
        <class>com.kuuhaku.model.persistent.shoukan.Senshi</class>
        <class>com.kuuhaku.model.persistent.shoukan.LocalizedDescription</class>
        <class>com.kuuhaku.model.persistent.shoukan.LocalizedString</class>

        <properties>
            <property name="jakarta.persistence.jdbc.driver" value="org.postgresql.Driver"/>

            <property name="hibernate.dialect" value="org.hibernate.dialect.PostgreSQLDialect"/>
            <property name="hibernate.jdbc.batch_size" value="30"/>
            <property name="hibernate.show_sql" value="false"/>
            <property name="hibernate.enable_lazy_load_no_trans" value="true"/>

            <property name="hibernate.c3p0.min_size" value="3"/>
            <property name="hibernate.c3p0.max_size" value="15"/>
            <property name="hibernate.c3p0.timeout" value="300"/>
            <property name="hibernate.c3p0.max_statements" value="50"/>
            <property name="hibernate.c3p0.idle_test_period" value="3000"/>
            <property name="hibernate.c3p0.preferredTestQuery" value="SELECT 1"/>
            <property name="hibernate.c3p0.testConnectionOnCheckout" value="true"/>

            <property name="hibernate.hbm2ddl.auto" value="update"/>
            <property name="hibernate.connection.characterEncoding" value="utf8"/>
            <property name="hibernate.connection.useUnicode" value="true"/>
            <property name="hibernate.connection.charSet" value="UTF-8"/>
        </properties>
    </persistence-unit>
</persistence>